fetchbio/__init__.py
fetchbio/main.py
fetchbio-0.1.3.dist-info/METADATA
fetchbio-0.1.3.dist-info/WHEEL
fetchbio-0.1.3.dist-info/top_level.txt
fetchbio-0.1.3.dist-info/RECORD
