Metadata-Version: 2.4
Name: fetchbio
Version: 0.1.3
Summary: 用来抓取生物数据的MCP服务
Requires-Python: >=3.12
Requires-Dist: httpx>=0.28.1
Requires-Dist: mcp>=1.13.1
